<game venue="Citizens Bank Park" date="May 20, 2007">
	<team type="away" id="TOR" name="Toronto Blue Jays">
		<player id="112381" first="Royce" last="Clayton" num="11" boxname="Clayton" rl="R" position="SS" status="A" bat_order="7" game_position="SS" avg=".256" hr="0" rbi="6"/>
		<player id="114031" first="Sal" last="Fasano" num="13" boxname="Fasano" rl="R" position="C" status="A" avg=".125" hr="1" rbi="2"/>
		<player id="122644" first="Matt" last="Stairs" num="24" boxname="Stairs" rl="R" position="D" status="A" bat_order="5" game_position="LF" avg=".317" hr="3" rbi="9"/>
		<player id="150359" first="A.J." last="Burnett" num="34" boxname="Burnett" rl="R" position="P" status="A" avg=".000" hr="0" rbi="0" wins="4" losses="3" era="3.99"/>
		<player id="219594" first="Tomo" last="Ohka" num="18" boxname="Ohka" rl="R" position="P" status="A" avg=".000" hr="0" rbi="0" wins="2" losses="4" era="5.52"/>
		<player id="461347" first="Jamie" last="Vermilyea" num="36" boxname="Vermilyea" rl="R" position="P" status="A" avg=".000" hr="0" rbi="0" wins="0" losses="0" era="0.00"/>
		<player id="452252" first="Adam" last="Lind" num="26" boxname="Lind" rl="L" position="LF" status="A" avg=".232" hr="4" rbi="12"/>
		<player id="451788" first="Shaun" last="Marcum" num="28" boxname="Marcum" rl="R" position="P" status="A" avg=".000" hr="0" rbi="0" wins="2" losses="2" era="4.13"/>
		<player id="446209" first="Jesse" last="Litsch" num="51" boxname="Litsch" rl="R" position="P" status="A" bat_order="9" game_position="P" avg=".000" hr="0" rbi="0" wins="1" losses="0" era="1.04"/>
		<player id="445163" first="Casey" last="Janssen" num="44" boxname="Janssen" rl="R" position="P" status="A" avg=".000" hr="0" rbi="0" wins="1" losses="0" era="0.92"/>
		<player id="440251" first="Ryan" last="Roberts" num="20" boxname="Roberts" rl="R" position="2B" status="A" avg=".143" hr="0" rbi="0"/>
		<player id="435618" first="Jeremy" last="Accardo" num="49" boxname="Accardo" rl="R" position="P" status="A" avg=".000" hr="0" rbi="0" wins="0" losses="0" era="0.00"/>
		<player id="431094" first="Aaron" last="Hill" num="2" boxname="Hill" rl="R" position="2B" status="A" bat_order="6" game_position="2B" avg=".277" hr="7" rbi="25"/>
		<player id="430661" first="Dustin" last="McGowan" num="29" boxname="McGowan" rl="R" position="P" status="A" avg=".000" hr="0" rbi="0" wins="0" losses="1" era="8.22"/>
		<player id="430630" first="Jason" last="Frasor" num="54" boxname="Frasor" rl="R" position="P" status="A" avg=".000" hr="0" rbi="0" wins="1" losses="2" era="5.51"/>
		<player id="425567" first="Alex" last="Rios" num="15" boxname="Rios" rl="R" position="RF" status="A" bat_order="1" game_position="RF" avg=".273" hr="8" rbi="22"/>
		<player id="425226" first="Brian" last="Tallet" num="56" boxname="Tallet" rl="L" position="P" status="A" avg=".000" hr="0" rbi="0" wins="0" losses="1" era="3.60"/>
		<player id="407489" first="Lyle" last="Overbay" num="17" boxname="Overbay" rl="L" position="1B" status="A" bat_order="2" game_position="1B" avg=".253" hr="6" rbi="21"/>
		<player id="346869" first="Josh" last="Towers" num="7" boxname="Towers" rl="R" position="P" status="A" avg=".000" hr="0" rbi="0" wins="1" losses="3" era="5.62"/>
		<player id="282993" first="Jason" last="Phillips" num="47" boxname="Phillips" rl="R" position="C" status="A" bat_order="8" game_position="C" avg=".239" hr="0" rbi="7"/>
		<player id="275933" first="Scott" last="Downs" num="37" boxname="Downs" rl="L" position="P" status="A" avg=".000" hr="0" rbi="0" wins="1" losses="0" era="1.72"/>
		<player id="150484" first="Vernon" last="Wells" num="10" boxname="Wells" rl="R" position="CF" status="A" bat_order="3" game_position="CF" avg=".279" hr="4" rbi="20"/>
		<player id="150348" first="John" last="McDonald" num="6" boxname="McDonald" rl="R" position="SS" status="A" avg=".274" hr="0" rbi="3"/>
		<player id="123245" first="Frank" last="Thomas" num="35" boxname="Thomas" rl="R" position="D" status="A" avg=".236" hr="5" rbi="18"/>
		<player id="136267" first="Troy" last="Glaus" num="25" boxname="Glaus" rl="R" position="3B" status="A" bat_order="4" game_position="3B" avg=".310" hr="8" rbi="21"/>
<coach position="first_base_coach" first="Marty" last="Pevey" id="120488" num="45"/><coach position="bullpen_coach" first="Bruce" last="Walton" id="123899" num="53"/><coach position="third_base_coach" first="Brian" last="Butterfield" id="427047" num="55"/><coach position="batting_coach" first="Mickey" last="Brantley" id="111398" num="14"/><coach position="manager" first="John" last="Gibbons" id="114744" num="5"/><coach position="coach" first="Alex" last="Andreopoulos" id="432938" num="61"/><coach position="bench_coach" first="Ernie" last="Whitt" id="124224" num="12"/><coach position="pitching_coach" first="Brad" last="Arnsberg" id="110336" num="38"/>	</team>
	<team type="home" id="PHI" name="Philadelphia Phillies">
		<player id="110134" first="Antonio" last="Alfonseca" num="57" boxname="Alfonseca" rl="R" position="P" status="A" avg=".000" hr="0" rbi="0" wins="2" losses="1" era="5.03"/>
		<player id="117758" first="Jon" last="Lieber" num="21" boxname="Lieber" rl="R" position="P" status="A" avg=".077" hr="0" rbi="1" wins="2" losses="2" era="3.00"/>
		<player id="119469" first="Jamie" last="Moyer" num="50" boxname="Moyer" rl="L" position="P" status="A" avg=".136" hr="0" rbi="0" wins="4" losses="3" era="4.37"/>
		<player id="150029" first="Jayson" last="Werth" num="28" boxname="Werth" rl="R" position="RF" status="A" avg=".237" hr="0" rbi="3"/>
		<player id="136500" first="Wes" last="Helms" num="18" boxname="Helms" rl="R" position="3B" status="A" avg=".270" hr="0" rbi="12"/>
		<player id="119865" first="Abraham" last="Nunez" num="3" boxname="Nunez" rl="R" position="3B" status="A" bat_order="7" game_position="3B" avg=".317" hr="0" rbi="8"/>
		<player id="150100" first="Pat" last="Burrell" num="5" boxname="Burrell" rl="R" position="LF" status="A" bat_order="5" game_position="LF" avg=".250" hr="5" rbi="21"/>
		<player id="150148" first="Rod" last="Barajas" num="2" boxname="Barajas" rl="R" position="C" status="A" bat_order="8" game_position="C" avg=".174" hr="2" rbi="4"/>
		<player id="150119" first="Freddy" last="Garcia" num="34" boxname="Garcia" rl="R" position="P" status="A" avg=".250" hr="0" rbi="2" wins="1" losses="3" era="4.86"/>
		<player id="430935" first="Cole" last="Hamels" num="35" boxname="Hamels" rl="L" position="P" status="A" avg=".174" hr="0" rbi="0" wins="6" losses="1" era="3.30"/>
		<player id="425785" first="Greg" last="Dobbs" num="19" boxname="Dobbs" rl="R" position="3B" status="A" bat_order="6" game_position="1B" avg=".283" hr="2" rbi="12"/>
		<player id="425664" first="Shane" last="Victorino" num="8" boxname="Victorino" rl="R" position="CF" status="A" bat_order="2" game_position="RF" avg=".270" hr="2" rbi="17"/>
		<player id="425564" first="Francisco" last="Rosario" num="54" boxname="Rosario" rl="R" position="P" status="A" avg=".000" hr="0" rbi="0" wins="0" losses="2" era="5.11"/>
		<player id="424925" first="Clay" last="Condrey" num="55" boxname="Condrey" rl="R" position="P" status="A" avg=".000" hr="0" rbi="0" wins="1" losses="0" era="9.00"/>
		<player id="408206" first="Brett" last="Myers" num="39" boxname="Myers" rl="R" position="P" status="A" avg=".000" hr="0" rbi="0" wins="1" losses="2" era="4.76"/>
		<player id="407783" first="Geoff" last="Geary" num="56" boxname="Geary" rl="R" position="P" status="A" avg=".000" hr="0" rbi="0" wins="0" losses="1" era="3.54"/>
		<player id="400284" first="Chase" last="Utley" num="26" boxname="Utley" rl="R" position="2B" status="A" bat_order="4" game_position="2B" avg=".298" hr="8" rbi="34"/>
		<player id="400120" first="Chris" last="Coste" num="27" boxname="Coste" rl="R" position="C" status="A" avg=".000" hr="0" rbi="0"/>
		<player id="470279" first="Yoel" last="Hernandez" num="44" boxname="Hernandez" rl="R" position="P" status="A" avg=".000" hr="0" rbi="0" wins="0" losses="0" era="3.86"/>
		<player id="466983" first="Fabio" last="Castro" num="52" boxname="Castro, F" rl="L" position="P" status="A" avg=".000" hr="0" rbi="0" wins="0" losses="0" era="12.27"/>
		<player id="456422" first="Michael" last="Bourn" num="9" boxname="Bourn" rl="R" position="RF" status="A" avg=".250" hr="0" rbi="1"/>
		<player id="434563" first="Carlos" last="Ruiz" num="51" boxname="Ruiz" rl="R" position="C" status="A" avg=".274" hr="3" rbi="17"/>
		<player id="400023" first="Aaron" last="Rowand" num="33" boxname="Rowand" rl="R" position="CF" status="A" bat_order="1" game_position="CF" avg=".331" hr="6" rbi="21"/>
		<player id="284566" first="Adam" last="Eaton" num="23" boxname="Eaton" rl="R" position="P" status="A" bat_order="9" game_position="P" avg=".143" hr="0" rbi="1" wins="3" losses="3" era="6.42"/>
		<player id="276519" first="Jimmy" last="Rollins" num="11" boxname="Rollins" rl="R" position="SS" status="A" bat_order="3" game_position="SS" avg=".276" hr="9" rbi="27"/>
<coach position="third_base_coach" first="Steve" last="Smith" id="427473" num="7"/><coach position="bullpen_coach" first="Ramon" last="Henderson" id="427214" num="31"/><coach position="coach" first="Mick" last="Billmeyer" id="434738" num="17"/><coach position="manager" first="Charlie" last="Manuel" id="118261" num="41"/><coach position="bench_coach" first="Jimy" last="Williams" id="124318" num="22"/><coach position="first_base_coach" first="Davey" last="Lopes" id="117912" num="15"/><coach position="pitching_coach" first="Rich" last="Dubee" id="433643" num="30"/><coach position="batting_coach" first="Milt" last="Thompson" id="123298" num="25"/>	</team>
<umpires><umpire position="home" name="Phil Cuzzi"/><umpire position="first" name="James Hoye"/><umpire position="second" name="Jerry Crawford"/><umpire position="third" name="Brian O'Nora"/></umpires></game>