<!--Copyright 2014 MLB Advanced Media, L.P.  Use of any content on this page acknowledges agreement to the terms posted here http://gdx.mlb.com/components/copyright.txt--><scores away_team="nyn" home_team="atl"><score inn="1" atbat_num="2" top_inning="Y" home="0" away="1" pbp="Ruben Tejada grounds out, shortstop Alex Gonzalez to first baseman Eric Hinske.   Jose Reyes scores.  "><atbat num="2" b="0" s="1" o="1" start_tfs="003449" start_tfs_zulu="2011-06-16T00:34:49Z" batter="514913" stand="R" b_height="5-11" pitcher="218596" p_throws="R" des="Ruben Tejada grounds out, shortstop Alex Gonzalez to first baseman Eric Hinske.   Jose Reyes scores.  " des_es="Ruben Tejada batea rodado de out a primera base Eric Hinske en jugada de infield fly.   Jose Reyes anota.  " event="Groundout" score="T" home_team_runs="0" away_team_runs="1"><pitch des="Called Strike" des_es="Strike cantado" id="11" type="S" tfs="003423" tfs_zulu="2011-06-16T00:34:23Z" x="112.45" y="130.38" on_3b="408314" sv_id="110615_203425" start_speed="91.9" end_speed="84.5" sz_top="3.08" sz_bot="1.45" pfx_x="-9.33" pfx_z="2.14" px="-0.418" pz="3.043" x0="-0.64" y0="50.0" z0="5.465" vx0="3.807" vy0="-134.693" vz0="-1.125" ax="-17.083" ay="30.127" az="-28.186" break_y="23.8" break_angle="29.8" break_length="7.3" pitch_type="SI" type_confidence="2.000" zone="1" nasty="62" spin_dir="256.859" spin_rate="1889.489"  cc="" mt=""/><pitch des="In play, run(s)" des_es="En juego, carrera(s)" id="12" type="X" tfs="003442" tfs_zulu="2011-06-16T00:34:42Z" x="95.28" y="151.10" on_3b="408314" sv_id="110615_203445" start_speed="76.8" end_speed="70.9" sz_top="3.11" sz_bot="1.46" pfx_x="7.57" pfx_z="-8.18" px="0.223" pz="2.066" x0="-0.882" y0="50.0" z0="5.652" vx0="0.271" vy0="-112.645" vz0="1.663" ax="9.614" ay="22.723" az="-42.482" break_y="23.8" break_angle="-12.9" break_length="13.8" pitch_type="CU" type_confidence="2.000" zone="5" nasty="21" spin_dir="43.004" spin_rate="1815.397"  cc="" mt=""/><runner id="408314" start="3B" end="" event="Groundout" score="T" rbi="T"/></atbat></score><score inn="4" atbat_num="25" top_inning="Y" home="0" away="3" pbp="Angel Pagan homers (2) on a fly ball to right field.    Daniel Murphy scores.  "><atbat num="25" b="1" s="1" o="0" start_tfs="012043" start_tfs_zulu="2011-06-16T01:20:43Z" batter="434636" stand="L" b_height="6-2" pitcher="218596" p_throws="R" des="Angel Pagan homers (2) on a fly ball to right field.    Daniel Murphy scores.  " des_es="Angel Pagan batea jonrón (2) con elevado por el jardín derecho.    Daniel Murphy anota.  " event="Home Run" score="T" home_team_runs="0" away_team_runs="3"><pitch des="Called Strike" des_es="Strike cantado" id="177" type="S" tfs="012102" tfs_zulu="2011-06-16T01:21:02Z" x="97.85" y="153.69" on_1b="502517" sv_id="110615_212105" start_speed="91.6" end_speed="85.3" sz_top="3.04" sz_bot="1.47" pfx_x="-5.61" pfx_z="8.26" px="0.158" pz="2.141" x0="-0.686" y0="50.0" z0="5.204" vx0="4.196" vy0="-134.195" vz0="-4.998" ax="-10.371" ay="25.476" az="-16.844" break_y="23.9" break_angle="28.4" break_length="4.4" pitch_type="FF" type_confidence=".835" zone="5" nasty="43" spin_dir="214.078" spin_rate="2000.960"  cc="" mt=""/><po des="Pickoff Attempt 1B"/><pitch des="Ball" des_es="Bola mala" id="179" type="B" tfs="012155" tfs_zulu="2011-06-16T01:21:55Z" x="179.40" y="98.43" on_1b="502517" sv_id="110615_212158" start_speed="75.5" end_speed="69.9" sz_top="3.16" sz_bot="1.4" pfx_x="7.98" pfx_z="-8.49" px="-2.614" pz="4.569" x0="-1.014" y0="50.0" z0="5.902" vx0="-5.759" vy0="-110.396" vz0="6.852" ax="9.887" ay="18.857" az="-42.626" break_y="23.8" break_angle="-12.2" break_length="13.9" pitch_type="CU" type_confidence="2.000" zone="11" nasty="12" spin_dir="43.408" spin_rate="1890.736"  cc="" mt=""/><pitch des="In play, run(s)" des_es="En juego, carrera(s)" id="180" type="X" tfs="012225" tfs_zulu="2011-06-16T01:22:25Z" x="81.55" y="151.97" on_1b="502517" sv_id="110615_212227" start_speed="85.9" end_speed="79.0" sz_top="3.13" sz_bot="1.53" pfx_x="-1.05" pfx_z="3.28" px="0.596" pz="2.233" x0="-0.722" y0="50.0" z0="5.383" vx0="3.606" vy0="-125.923" vz0="-2.399" ax="-1.676" ay="26.894" az="-26.863" break_y="23.8" break_angle="2.0" break_length="7.0" pitch_type="FC" type_confidence="2.000" zone="6" nasty="37" spin_dir="197.513" spin_rate="641.635"  cc="" mt=""/><runner id="502517" start="1B" end="" event="Pickoff Attempt 1B" score="T" rbi="T" earned="T"/><runner id="434636" start="" end="" event="Pickoff Attempt 1B" score="T" rbi="T" earned="T"/></atbat></score><score inn="7" atbat_num="49" top_inning="Y" home="0" away="4" pbp="Jose Reyes grounds out to first baseman Eric Hinske.   Lucas Duda scores.    Josh Thole to 3rd.    Willie Harris to 2nd.  "><action b="0" s="0" o="1" des="Pitching Change: Scott Linebrink replaces Cristhian Martinez, batting 9th.  " des_es="Cambio de Lanzador: Scott Linebrink reemplaza a Cristhian Martinez, bateando noveno.  " event="Pitching Substitution" tfs="032819" tfs_zulu="2011-06-16T03:28:19Z" player="276530" pitch="5"/><action b="0" s="0" o="1" des="Coaching visit to mound.  " des_es="" event="Game Advisory" tfs="032756" tfs_zulu="2011-06-16T03:27:56Z" player="408314" pitch="5"/><atbat num="49" b="0" s="1" o="2" start_tfs="032958" start_tfs_zulu="2011-06-16T03:29:58Z" batter="408314" stand="L" b_height="6-1" pitcher="276530" p_throws="R" des="Jose Reyes grounds out to first baseman Eric Hinske.   Lucas Duda scores.    Josh Thole to 3rd.    Willie Harris to 2nd.  " des_es="Jose Reyes batea rodado de out a primera base Eric Hinske en jugada de infield fly.   Lucas Duda anota  Josh Thole a 3ra.    Willie Harris a 2da.  " event="Groundout" score="T" home_team_runs="0" away_team_runs="4"><pitch des="Foul" des_es="Foul" id="387" type="S" tfs="033010" tfs_zulu="2011-06-16T03:30:10Z" x="106.44" y="126.93" on_1b="407483" on_2b="489365" on_3b="446263" sv_id="110615_233013" start_speed="91.9" end_speed="84.0" sz_top="2.98" sz_bot="1.47" pfx_x="-8.0" pfx_z="9.73" px="-0.182" pz="3.197" x0="-1.946" y0="50.0" z0="6.232" vx0="7.416" vy0="-134.437" vz0="-5.306" ax="-14.541" ay="31.102" az="-14.429" break_y="23.7" break_angle="39.4" break_length="4.5" pitch_type="SI" type_confidence=".000" zone="11" nasty="58" spin_dir="219.332" spin_rate="2475.772"  cc="" mt=""/><pitch des="In play, run(s)" des_es="En juego, carrera(s)" id="388" type="X" tfs="033046" tfs_zulu="2011-06-16T03:30:46Z" x="79.83" y="140.74" on_1b="407483" on_2b="489365" on_3b="446263" sv_id="110615_233048" start_speed="81.4" end_speed="75.5" sz_top="2.98" sz_bot="1.47" pfx_x="3.32" pfx_z="-4.62" px="0.619" pz="2.762" x0="-1.956" y0="50.0" z0="6.298" vx0="5.041" vy0="-119.216" vz0="-0.081" ax="4.766" ay="23.282" az="-38.736" break_y="23.8" break_angle="-8.2" break_length="11.0" pitch_type="SL" type_confidence=".913" zone="3" nasty="45" spin_dir="35.990" spin_rate="986.954"  cc="" mt=""/><runner id="407483" start="1B" end="2B" event="Groundout"/><runner id="489365" start="2B" end="3B" event="Groundout"/><runner id="446263" start="3B" end="" event="Groundout" score="T" rbi="T" earned="T"/></atbat></score></scores>