<!--Copyright 2014 MLB Advanced Media, L.P.  Use of any content on this page acknowledges agreement to the terms posted here http://gdx.mlb.com/components/copyright.txt--><boxscore game_id="2011/06/08/tbamlb-anamlb-1" game_pk="287836" venue_id="1" venue_name="Angel Stadium of Anaheim" home_sport_code="mlb" away_team_code="tba" home_team_code="ana" away_id="139" home_id="108" away_fname="Tampa Bay Rays" home_fname="Los Angeles Angels" away_sname="Tampa Bay" home_sname="LA Angels" date="June 8, 2011" away_wins="33" away_loss="29" home_wins="30" home_loss="34" status_ind="F">
   <linescore away_team_runs="4" home_team_runs="3" away_team_hits="7" home_team_hits="8" away_team_errors="0" home_team_errors="2">
      <inning_line_score away="0" home="0" inning="1"></inning_line_score>
      <inning_line_score away="0" home="0" inning="2"></inning_line_score>
      <inning_line_score away="1" home="0" inning="3"></inning_line_score>
      <inning_line_score away="0" home="0" inning="4"></inning_line_score>
      <inning_line_score away="0" home="0" inning="5"></inning_line_score>
      <inning_line_score away="0" home="0" inning="6"></inning_line_score>
      <inning_line_score away="1" home="0" inning="7"></inning_line_score>
      <inning_line_score away="1" home="3" inning="8"></inning_line_score>
      <inning_line_score away="0" home="0" inning="9"></inning_line_score>
      <inning_line_score away="1" home="0" inning="10"></inning_line_score>
   </linescore>
   <pitching team_flag="away" out="30" h="8" r="3" er="3" bb="4" so="11" hr="0" bf="41" era="3.69">
      <pitcher id="448306" name="Shields" name_display_first_last="James Shields" pos="P" out="21" bf="30" er="3" r="3" h="7" so="8" hr="0" bb="3" np="101" s="62" w="5" l="4" sv="0" bs="0" hld="0" s_ip="94.2" s_h="77" s_r="32" s_er="30" s_bb="24" s_so="93" era="2.85"></pitcher>
      <pitcher id="459987" name="Ramos, C" name_display_first_last="Cesar Ramos" pos="P" out="0" bf="1" er="0" r="0" h="1" so="0" hr="0" bb="0" np="2" s="1" w="0" l="1" sv="0" bs="2" hld="1" s_ip="18.2" s_h="14" s_r="8" s_er="7" s_bb="9" s_so="15" era="3.38" blown_save="true" note="(BS, 2)">(BS, 2)</pitcher>
      <pitcher id="407908" name="Peralta, Jo" name_display_first_last="Joel Peralta" pos="P" out="3" bf="3" er="0" r="0" h="0" so="1" hr="0" bb="0" np="12" s="9" w="2" l="3" sv="0" bs="1" hld="10" s_ip="30.2" s_h="18" s_r="13" s_er="12" s_bb="10" s_so="22" era="3.52"></pitcher>
      <pitcher id="407297" name="Cruz, J" name_display_first_last="Juan Cruz" pos="P" out="3" bf="3" er="0" r="0" h="0" so="1" hr="0" bb="0" np="15" s="9" w="3" l="0" sv="0" bs="0" hld="1" s_ip="22.1" s_h="13" s_r="9" s_er="9" s_bb="17" s_so="19" era="3.63" win="true" note="(W, 3-0)"></pitcher>
      <pitcher id="150035" name="Farnsworth" name_display_first_last="Kyle Farnsworth" pos="P" out="3" bf="4" er="0" r="0" h="0" so="1" hr="0" bb="1" np="19" s="8" w="2" l="0" sv="13" bs="1" hld="0" s_ip="23.0" s_h="14" s_r="4" s_er="3" s_bb="2" s_so="15" era="1.17" save="true" note="(S, 13)"></pitcher>
   </pitching>
   <batting team_flag="home" ab="36" r="3" h="8" d="4" t="0" hr="0" rbi="3" bb="4" po="30" da="11" so="11" lob="18" avg=".254">
      <batter id="430895" name="Izturis, M" name_display_first_last="Maicer Izturis" pos="SS" bo="100" ab="4" po="2" r="1" a="5" bb="0" sac="0" t="0" sf="0" h="2" e="0" d="0" hbp="1" so="1" hr="0" rbi="0" lob="0" fldg="1.000" sb="0" cs="0" s_hr="3" s_rbi="16" s_h="61" s_bb="18" s_r="25" s_so="31" avg=".292" ao="1"></batter>
      <batter id="116338" name="Hunter, To" name_display_first_last="Torii Hunter" pos="RF" bo="200" ab="5" po="1" r="1" a="0" bb="0" sac="0" t="0" sf="0" h="2" e="0" d="1" hbp="0" so="0" hr="0" rbi="0" lob="3" fldg="1.000" sb="0" cs="0" s_hr="8" s_rbi="32" s_h="58" s_bb="28" s_r="25" s_so="53" avg=".238" go="4" ao="0" gidp="1"></batter>
      <batter id="430948" name="Callaspo" name_display_first_last="Alberto Callaspo" pos="3B" bo="300" ab="3" po="0" r="1" a="3" bb="2" sac="0" t="0" sf="0" h="0" e="0" d="0" hbp="0" so="1" hr="0" rbi="0" lob="1" fldg="1.000" sb="0" cs="0" s_hr="3" s_rbi="28" s_h="65" s_bb="24" s_r="21" s_so="18" avg=".290" ao="2"></batter>
      <batter id="430947" name="Aybar" name_display_first_last="Erick Aybar" pos="PR" bo="301" ab="0" po="0" r="0" a="0" bb="0" sac="0" t="0" sf="0" h="0" e="0" d="0" hbp="0" so="0" hr="0" rbi="0" lob="0" fldg=".000" sb="0" cs="0" s_hr="3" s_rbi="21" s_h="59" s_bb="10" s_r="23" s_so="31" avg=".296" note="1-" ao="0"></batter>
      <batter id="110029" name="Abreu" name_display_first_last="Bobby Abreu" pos="DH" bo="400" ab="4" po="0" r="0" a="0" bb="1" sac="0" t="0" sf="0" h="1" e="0" d="1" hbp="0" so="1" hr="0" rbi="3" lob="1" fldg=".000" sb="0" cs="0" s_hr="2" s_rbi="28" s_h="66" s_bb="42" s_r="25" s_so="47" avg=".289" ao="2"></batter>
      <batter id="435062" name="Kendrick, H" name_display_first_last="Howie Kendrick" pos="2B" bo="500" ab="5" po="2" r="0" a="1" bb="0" sac="0" t="0" sf="0" h="1" e="1" d="1" hbp="0" so="1" hr="0" rbi="0" lob="2" fldg=".750" sb="0" cs="0" s_hr="7" s_rbi="18" s_h="59" s_bb="16" s_r="31" s_so="46" avg=".301" go="2" ao="1"></batter>
      <batter id="444432" name="Trumbo" name_display_first_last="Mark Trumbo" pos="1B" bo="600" ab="4" po="11" r="0" a="0" bb="0" sac="0" t="0" sf="0" h="0" e="0" d="0" hbp="0" so="2" hr="0" rbi="0" lob="3" fldg="1.000" sb="0" cs="0" s_hr="11" s_rbi="29" s_h="53" s_bb="13" s_r="23" s_so="49" avg=".257" go="1" ao="1"></batter>
      <batter id="150484" name="Wells, V" name_display_first_last="Vernon Wells" pos="LF" bo="700" ab="3" po="3" r="0" a="0" bb="1" sac="0" t="0" sf="0" h="0" e="0" d="0" hbp="0" so="2" hr="0" rbi="0" lob="3" fldg="1.000" sb="0" cs="0" s_hr="4" s_rbi="13" s_h="26" s_bb="8" s_r="18" s_so="33" avg=".176" ao="1"></batter>
      <batter id="488721" name="Bourjos" name_display_first_last="Peter Bourjos" pos="CF" bo="800" ab="4" po="4" r="0" a="0" bb="0" sac="0" t="0" sf="0" h="2" e="0" d="1" hbp="0" so="1" hr="0" rbi="0" lob="2" fldg="1.000" sb="0" cs="0" s_hr="3" s_rbi="13" s_h="53" s_bb="15" s_r="27" s_so="63" avg=".245" ao="1"></batter>
      <batter id="425772" name="Mathis" name_display_first_last="Jeff Mathis" pos="C" bo="900" ab="2" po="5" r="0" a="1" bb="0" sac="0" t="0" sf="0" h="0" e="0" d="0" hbp="0" so="1" hr="0" rbi="0" lob="2" fldg="1.000" sb="0" cs="0" s_hr="1" s_rbi="10" s_h="23" s_bb="5" s_r="9" s_so="30" avg=".204" ao="1"></batter>
      <batter id="474233" name="Conger" name_display_first_last="Hank Conger" pos="PH-C" bo="901" ab="2" po="2" r="0" a="0" bb="0" sac="0" t="0" sf="0" h="0" e="1" d="0" hbp="0" so="1" hr="0" rbi="0" lob="1" fldg=".667" sb="0" cs="0" s_hr="3" s_rbi="12" s_h="26" s_bb="9" s_r="9" s_so="23" avg=".228" note="a-" go="1" ao="0"></batter>
      <batter id="450308" name="Weaver" name_display_first_last="Jered Weaver" pos="P" ab="0" po="0" r="0" a="1" bb="0" sac="0" t="0" sf="0" h="0" e="0" d="0" hbp="0" so="0" hr="0" rbi="0" lob="0" fldg="1.000" sb="0" cs="0" s_hr="0" s_rbi="0" s_h="0" s_bb="0" s_r="0" s_so="0" avg=".000" ao="0"></batter>
      <batter id="275933" name="Downs, S" name_display_first_last="Scott Downs" pos="P" ab="0" po="0" r="0" a="0" bb="0" sac="0" t="0" sf="0" h="0" e="0" d="0" hbp="0" so="0" hr="0" rbi="0" lob="0" fldg=".000" sb="0" cs="0" s_hr="0" s_rbi="0" s_h="0" s_bb="0" s_r="0" s_so="0" avg=".000" ao="0"></batter>
      <batter id="477229" name="Walden" name_display_first_last="Jordan Walden" pos="P" ab="0" po="0" r="0" a="0" bb="0" sac="0" t="0" sf="0" h="0" e="0" d="0" hbp="0" so="0" hr="0" rbi="0" lob="0" fldg=".000" sb="0" cs="0" s_hr="0" s_rbi="0" s_h="0" s_bb="0" s_r="0" s_so="0" avg=".000" ao="0"></batter>
      <batter id="407845" name="Rodney" name_display_first_last="Fernando Rodney" pos="P" ab="0" po="0" r="0" a="0" bb="0" sac="0" t="0" sf="0" h="0" e="0" d="0" hbp="0" so="0" hr="0" rbi="0" lob="0" fldg=".000" sb="0" cs="0" s_hr="0" s_rbi="0" s_h="0" s_bb="0" s_r="0" s_so="0" avg=".000" ao="0"></batter>
      <note><![CDATA[<span>a-Grounded out for Mathis in the 7th. </span><br/><span>1-Ran for Callaspo in the 10th. </span>]]>
      </note>
      <text_data><![CDATA[<b>BATTING</b><br/><span><b>2B</b>: Kendrick, H (14, Shields), Hunter, To (10, Shields), Bourjos (9, Shields), Abreu (17, Ramos, C).</span><br/><span><b>TB</b>: Kendrick, H 2; Bourjos 3; Hunter, To 3; Abreu 2; Izturis, M 2.</span><br/><span><b>RBI</b>: Abreu 3 (28).</span><br/><span><b>Runners left in scoring position, 2 out</b>: Bourjos 2; Callaspo; Conger; Wells, V; Kendrick, H.</span><br/><span><b>GIDP</b>: Hunter, To.</span><br/><b>Team RISP</b>: 2-for-13.<br/><b>Team LOB</b>: 8.<br/><br/><b>BASERUNNING</b><br/><span><b>PO</b>: Izturis, M (1st base by Shields).</span><br/><br/><b>FIELDING</b><br/><span><b>E</b>: Kendrick, H (2, throw), Conger (3, throw).</span><br/><span><b>Pickoffs</b>: Weaver (Upton, B at 2nd base).</span><br/><br/>]]>
      </text_data>
   </batting>
   <pitching team_flag="home" out="30" h="7" r="4" er="4" bb="2" so="7" hr="1" bf="38" era="3.44">
      <pitcher id="450308" name="Weaver" name_display_first_last="Jered Weaver" pos="P" out="23" bf="29" er="3" r="3" h="6" so="5" hr="1" bb="1" np="121" s="77" w="7" l="4" sv="0" bs="0" hld="0" s_ip="100.1" s_h="70" s_r="26" s_er="25" s_bb="25" s_so="90" era="2.24"></pitcher>
      <pitcher id="275933" name="Downs, S" name_display_first_last="Scott Downs" pos="P" out="1" bf="1" er="0" r="0" h="0" so="1" hr="0" bb="0" np="4" s="3" w="3" l="2" sv="0" bs="1" hld="8" s_ip="18.1" s_h="14" s_r="3" s_er="3" s_bb="5" s_so="9" era="1.47"></pitcher>
      <pitcher id="477229" name="Walden" name_display_first_last="Jordan Walden" pos="P" out="3" bf="3" er="0" r="0" h="0" so="1" hr="0" bb="0" np="13" s="10" w="0" l="1" sv="13" bs="3" hld="2" s_ip="27.1" s_h="22" s_r="9" s_er="9" s_bb="13" s_so="29" era="2.96"></pitcher>
      <pitcher id="407845" name="Rodney" name_display_first_last="Fernando Rodney" pos="P" out="3" bf="5" er="1" r="1" h="1" so="0" hr="0" bb="1" np="25" s="16" w="2" l="3" sv="3" bs="3" hld="10" s_ip="22.0" s_h="16" s_r="10" s_er="10" s_bb="15" s_so="18" era="4.09" loss="true" note="(L, 2-3)"></pitcher>
   </pitching>
   <batting team_flag="away" ab="35" r="4" h="7" d="1" t="1" hr="1" rbi="4" bb="2" po="30" da="9" so="7" lob="10" avg=".244">
      <batter id="113028" name="Damon" name_display_first_last="Johnny Damon" pos="DH" bo="100" ab="4" po="0" r="1" a="0" bb="1" sac="0" t="0" sf="0" h="0" e="0" d="0" hbp="0" so="0" hr="0" rbi="0" lob="1" fldg=".000" sb="0" cs="1" s_hr="7" s_rbi="31" s_h="65" s_bb="14" s_r="27" s_so="31" avg=".279" go="2" ao="2"></batter>
      <batter id="450314" name="Zobrist" name_display_first_last="Ben Zobrist" pos="2B" bo="200" ab="5" po="2" r="0" a="2" bb="0" sac="0" t="1" sf="0" h="2" e="0" d="0" hbp="0" so="1" hr="0" rbi="1" lob="1" fldg="1.000" sb="1" cs="0" s_hr="9" s_rbi="35" s_h="60" s_bb="26" s_r="35" s_so="51" avg=".259" go="1" ao="1"></batter>
      <batter id="459964" name="Joyce" name_display_first_last="Matt Joyce" pos="RF" bo="300" ab="4" po="0" r="1" a="0" bb="0" sac="0" t="0" sf="0" h="1" e="0" d="0" hbp="0" so="3" hr="0" rbi="0" lob="2" fldg=".000" sb="0" cs="0" s_hr="10" s_rbi="34" s_h="66" s_bb="21" s_r="37" s_so="42" avg=".338" ao="0"></batter>
      <batter id="425834" name="Upton, B" name_display_first_last="B.J. Upton" pos="CF" bo="400" ab="4" po="5" r="0" a="0" bb="0" sac="0" t="0" sf="0" h="1" e="0" d="0" hbp="0" so="2" hr="0" rbi="0" lob="2" fldg="1.000" sb="0" cs="0" s_hr="8" s_rbi="30" s_h="47" s_bb="27" s_r="32" s_so="62" avg=".228" ao="1"></batter>
      <batter id="425773" name="Kotchman" name_display_first_last="Casey Kotchman" pos="1B" bo="500" ab="4" po="8" r="0" a="0" bb="0" sac="0" t="0" sf="0" h="0" e="0" d="0" hbp="0" so="0" hr="0" rbi="0" lob="3" fldg="1.000" sb="0" cs="0" s_hr="2" s_rbi="12" s_h="47" s_bb="11" s_r="14" s_so="15" avg=".341" go="2" ao="2"></batter>
      <batter id="448605" name="Ruggiano" name_display_first_last="Justin Ruggiano" pos="LF" bo="600" ab="4" po="1" r="0" a="0" bb="0" sac="0" t="0" sf="0" h="1" e="0" d="1" hbp="0" so="1" hr="0" rbi="1" lob="0" fldg="1.000" sb="0" cs="0" s_hr="2" s_rbi="7" s_h="6" s_bb="3" s_r="3" s_so="5" avg=".250" go="2" ao="0"></batter>
      <batter id="150479" name="Lopez, F" name_display_first_last="Felipe Lopez" pos="3B" bo="700" ab="3" po="0" r="0" a="0" bb="0" sac="0" t="0" sf="0" h="0" e="0" d="0" hbp="0" so="0" hr="0" rbi="0" lob="1" fldg=".000" sb="0" cs="0" s_hr="2" s_rbi="8" s_h="21" s_bb="4" s_r="8" s_so="28" avg=".216" go="1" ao="2"></batter>
      <batter id="446481" name="Rodriguez, S" name_display_first_last="Sean Rodriguez" pos="3B" bo="701" ab="0" po="0" r="0" a="0" bb="0" sac="0" t="0" sf="0" h="0" e="0" d="0" hbp="0" so="0" hr="0" rbi="0" lob="0" fldg=".000" sb="0" cs="0" s_hr="2" s_rbi="10" s_h="26" s_bb="12" s_r="15" s_so="38" avg=".208" ao="0"></batter>
      <batter id="444379" name="Jaso" name_display_first_last="John Jaso" pos="PH-C" bo="702" ab="0" po="1" r="1" a="0" bb="1" sac="0" t="0" sf="0" h="0" e="0" d="0" hbp="0" so="0" hr="0" rbi="0" lob="0" fldg="1.000" sb="1" cs="0" s_hr="3" s_rbi="14" s_h="29" s_bb="12" s_r="15" s_so="18" avg=".234" note="a-" ao="0"></batter>
      <batter id="431159" name="Shoppach" name_display_first_last="Kelly Shoppach" pos="C" bo="800" ab="3" po="10" r="0" a="0" bb="0" sac="0" t="0" sf="0" h="0" e="0" d="0" hbp="0" so="0" hr="0" rbi="0" lob="0" fldg="1.000" sb="0" cs="0" s_hr="2" s_rbi="8" s_h="14" s_bb="7" s_r="5" s_so="35" avg=".159" go="3" ao="0"></batter>
      <batter id="446334" name="Longoria" name_display_first_last="Evan Longoria" pos="PH-3B" bo="801" ab="1" po="0" r="0" a="1" bb="0" sac="0" t="0" sf="0" h="1" e="0" d="0" hbp="0" so="0" hr="0" rbi="0" lob="0" fldg="1.000" sb="0" cs="0" s_hr="4" s_rbi="13" s_h="29" s_bb="17" s_r="17" s_so="22" avg=".252" note="b-" ao="0"></batter>
      <batter id="458582" name="Brignac" name_display_first_last="Reid Brignac" pos="SS" bo="900" ab="3" po="2" r="1" a="5" bb="0" sac="1" t="0" sf="0" h="1" e="0" d="0" hbp="0" so="0" hr="1" rbi="2" lob="0" fldg="1.000" sb="0" cs="0" s_hr="1" s_rbi="8" s_h="23" s_bb="4" s_r="12" s_so="31" avg=".184" go="1" ao="2"></batter>
      <batter id="448306" name="Shields" name_display_first_last="James Shields" pos="P" ab="0" po="1" r="0" a="1" bb="0" sac="0" t="0" sf="0" h="0" e="0" d="0" hbp="0" so="0" hr="0" rbi="0" lob="0" fldg="1.000" sb="0" cs="0" s_hr="0" s_rbi="1" s_h="0" s_bb="0" s_r="0" s_so="1" avg=".000" ao="0"></batter>
      <batter id="459987" name="Ramos, C" name_display_first_last="Cesar Ramos" pos="P" ab="0" po="0" r="0" a="0" bb="0" sac="0" t="0" sf="0" h="0" e="0" d="0" hbp="0" so="0" hr="0" rbi="0" lob="0" fldg=".000" sb="0" cs="0" s_hr="0" s_rbi="0" s_h="0" s_bb="0" s_r="0" s_so="0" avg=".000" ao="0"></batter>
      <batter id="407908" name="Peralta, Jo" name_display_first_last="Joel Peralta" pos="P" ab="0" po="0" r="0" a="0" bb="0" sac="0" t="0" sf="0" h="0" e="0" d="0" hbp="0" so="0" hr="0" rbi="0" lob="0" fldg=".000" sb="0" cs="0" s_hr="0" s_rbi="0" s_h="0" s_bb="0" s_r="0" s_so="0" avg=".000" ao="0"></batter>
      <batter id="407297" name="Cruz, J" name_display_first_last="Juan Cruz" pos="P" ab="0" po="0" r="0" a="0" bb="0" sac="0" t="0" sf="0" h="0" e="0" d="0" hbp="0" so="0" hr="0" rbi="0" lob="0" fldg=".000" sb="0" cs="0" s_hr="0" s_rbi="0" s_h="0" s_bb="0" s_r="0" s_so="0" avg=".000" ao="0"></batter>
      <batter id="150035" name="Farnsworth" name_display_first_last="Kyle Farnsworth" pos="P" ab="0" po="0" r="0" a="0" bb="0" sac="0" t="0" sf="0" h="0" e="0" d="0" hbp="0" so="0" hr="0" rbi="0" lob="0" fldg=".000" sb="0" cs="0" s_hr="0" s_rbi="0" s_h="0" s_bb="0" s_r="0" s_so="0" avg=".000" ao="0"></batter>
      <note><![CDATA[<span>a-Walked for Rodriguez, S in the 10th. b-Singled for Shoppach in the 10th. </span>]]>
      </note>
      <text_data><![CDATA[<b>BATTING</b><br/><span><b>2B</b>: Ruggiano (1, Weaver).</span><br/><span><b>3B</b>: Zobrist (3, Weaver).</span><br/><span><b>HR</b>: Brignac (1, 3rd inning off Weaver, 0 on, 2 out).</span><br/><span><b>TB</b>: Longoria; Ruggiano 2; Upton, B; Joyce; Zobrist 4; Brignac 4.</span><br/><span><b>RBI</b>: Brignac 2 (8), Ruggiano (7), Zobrist (35).</span><br/><span><b>2-out RBI</b>: Brignac; Ruggiano; Zobrist.</span><br/><span><b>Runners left in scoring position, 2 out</b>: Kotchman; Lopez, F; Joyce; Zobrist.</span><br/><span><b>SAC</b>: Brignac.</span><br/><b>Team RISP</b>: 1-for-6.<br/><b>Team LOB</b>: 4.<br/><br/><b>BASERUNNING</b><br/><span><b>SB</b>: Zobrist (7, 2nd base off Weaver/Mathis), Jaso (1, 3rd base off Rodney/Conger).</span><br/><span><b>CS</b>: Damon (2, 2nd base by Weaver/Mathis).</span><br/><span><b>PO</b>: Upton, B (2nd base by Weaver).</span><br/><br/><b>FIELDING</b><br/><span><b>DP</b>: (Brignac-Zobrist-Kotchman).</span><br/><span><b>Pickoffs</b>: Shields (Izturis, M at 1st base).</span><br/><br/>]]>
      </text_data>
   </batting>
   <game_info><![CDATA[<span>Shields pitched to 3 batters in the 8th.</span><br/><span>Ramos, C pitched to 1 batter in the 8th.</span><br/><br/><span><b>WP</b>: Weaver.</span><br/><span><b>HBP</b>: Izturis, M (by Shields).</span><br/><span><b>Pitches-strikes</b>: Shields 101-62, Ramos, C 2-1, Peralta, Jo 12-9, Cruz, J 15-9, Farnsworth 19-8, Weaver 121-77, Downs, S 4-3, Walden 13-10, Rodney 25-16.</span><br/><span><b>Groundouts-flyouts</b>: Shields 5-4, Ramos, C 0-0, Peralta, Jo 1-0, Cruz, J 0-1, Farnsworth 1-1, Weaver 7-7, Downs, S 0-0, Walden 2-0, Rodney 3-0.</span><br/><span><b>Batters faced</b>: Shields 30, Ramos, C 1, Peralta, Jo 3, Cruz, J 3, Farnsworth 4, Weaver 29, Downs, S 1, Walden 3, Rodney 5.</span><br/><span><b>Inherited runners-scored</b>: Ramos, C 3-3, Peralta, Jo 1-0, Downs, S 1-0.</span><br/><b>Umpires</b>: HP: Scott Barry. 1B: John Hirschbeck. 2B: Wally Bell. 3B: Laz Diaz. <br/><b>Weather</b>: 65 degrees, clear.<br/><b>Wind</b>: 10 mph, Out to RF.<br/><b>T</b>: 3:16.<br/><b>Att</b>: 33,157.<br/><b>Venue</b>: Angel Stadium of Anaheim.<br/><b>June 8, 2011</b><br/>]]>
   </game_info>
</boxscore>