<!--Copyright 2014 MLB Advanced Media, L.P.  Use of any content on this page acknowledges agreement to the terms posted here http://gdx.mlb.com/components/copyright.txt--><hitchart><hip des="Flyout" x="65.26" y="88.35" batter="457788" pitcher="431162" type="O" team="A" inning="1"/><hip des="Single" x="126.51" y="166.67" batter="518792" pitcher="431162" type="H" team="A" inning="1"/><hip des="Single" x="77.31" y="108.43" batter="116706" pitcher="431162" type="H" team="A" inning="1"/><hip des="Groundout" x="109.44" y="152.61" batter="435263" pitcher="431162" type="O" team="A" inning="1"/><hip des="Single" x="112.45" y="81.33" batter="461416" pitcher="117955" type="H" team="H" inning="1"/><hip des="Groundout" x="109.44" y="152.61" batter="430583" pitcher="117955" type="O" team="H" inning="1"/><hip des="Groundout" x="122.49" y="147.59" batter="407861" pitcher="117955" type="O" team="H" inning="1"/><hip des="Groundout" x="109.44" y="151.61" batter="518692" pitcher="431162" type="O" team="A" inning="2"/><hip des="Double" x="53.21" y="121.49" batter="519203" pitcher="117955" type="H" team="H" inning="2"/><hip des="Groundout" x="141.57" y="157.63" batter="457727" pitcher="117955" type="O" team="H" inning="2"/><hip des="Single" x="76.31" y="113.45" batter="460026" pitcher="117955" type="H" team="H" inning="2"/><hip des="Pop Out" x="145.58" y="159.64" batter="471868" pitcher="117955" type="O" team="H" inning="2"/><hip des="Groundout" x="110.44" y="173.69" batter="434661" pitcher="431162" type="O" team="A" inning="3"/><hip des="Single" x="110.44" y="156.63" batter="461416" pitcher="117955" type="H" team="H" inning="3"/><hip des="Flyout" x="183.73" y="67.27" batter="430583" pitcher="117955" type="O" team="H" inning="3"/><hip des="Groundout" x="115.46" y="161.65" batter="407886" pitcher="117955" type="O" team="H" inning="3"/><hip des="Flyout" x="172.69" y="94.38" batter="519203" pitcher="117955" type="O" team="H" inning="3"/><hip des="Groundout" x="147.59" y="160.64" batter="116706" pitcher="431162" type="O" team="A" inning="4"/><hip des="Groundout" x="136.55" y="152.61" batter="435263" pitcher="431162" type="O" team="A" inning="4"/><hip des="Pop Out" x="158.63" y="189.76" batter="457727" pitcher="117955" type="O" team="H" inning="4"/><hip des="Groundout" x="100.40" y="167.67" batter="460026" pitcher="117955" type="O" team="H" inning="4"/><hip des="Groundout" x="113.45" y="172.69" batter="471868" pitcher="117955" type="O" team="H" inning="4"/><hip des="Groundout" x="112.45" y="159.64" batter="462564" pitcher="431162" type="O" team="A" inning="5"/><hip des="Groundout" x="112.45" y="158.63" batter="136460" pitcher="431162" type="O" team="A" inning="5"/><hip des="Groundout" x="118.47" y="149.60" batter="431162" pitcher="117955" type="O" team="H" inning="5"/><hip des="Groundout" x="106.43" y="153.61" batter="430583" pitcher="117955" type="O" team="H" inning="5"/><hip des="Groundout" x="124.50" y="178.71" batter="434661" pitcher="431162" type="O" team="A" inning="6"/><hip des="Lineout" x="99.40" y="88.35" batter="457788" pitcher="431162" type="O" team="A" inning="6"/><hip des="Groundout" x="141.57" y="155.62" batter="407861" pitcher="117955" type="O" team="H" inning="6"/><hip des="Groundout" x="143.57" y="155.62" batter="407886" pitcher="117955" type="O" team="H" inning="6"/><hip des="Double" x="195.78" y="51.20" batter="519203" pitcher="117955" type="H" team="H" inning="6"/><hip des="Single" x="114.46" y="177.71" batter="457727" pitcher="117955" type="H" team="H" inning="6"/><hip des="Single" x="194.78" y="121.49" batter="471868" pitcher="117955" type="H" team="H" inning="6"/><hip des="Single" x="124.50" y="100.40" batter="431162" pitcher="117955" type="H" team="H" inning="6"/><hip des="Error" x="124.50" y="100.40" batter="431162" pitcher="117955" type="E" team="H" inning="6"/><hip des="Groundout" x="147.59" y="170.68" batter="461416" pitcher="430941" type="O" team="H" inning="6"/><hip des="Single" x="151.61" y="92.37" batter="518792" pitcher="431162" type="H" team="A" inning="7"/><hip des="Flyout" x="95.38" y="41.16" batter="435263" pitcher="431162" type="O" team="A" inning="7"/><hip des="Home Run" x="127.51" y="19.08" batter="518692" pitcher="431162" type="H" team="A" inning="7"/><hip des="Lineout" x="165.66" y="98.39" batter="430583" pitcher="446003" type="O" team="H" inning="7"/><hip des="Single" x="160.64" y="107.43" batter="407861" pitcher="446003" type="H" team="H" inning="7"/><hip des="Double" x="90.36" y="41.16" batter="407886" pitcher="446003" type="H" team="H" inning="7"/><hip des="Triple" x="84.34" y="41.16" batter="457727" pitcher="446003" type="H" team="H" inning="7"/><hip des="Field Error" x="141.57" y="157.63" batter="471868" pitcher="446003" type="E" team="H" inning="7"/><hip des="Home Run" x="44.18" y="40.16" batter="461882" pitcher="446003" type="H" team="H" inning="7"/><hip des="Lineout" x="137.55" y="86.35" batter="407861" pitcher="450852" type="O" team="H" inning="7"/><hip des="Groundout" x="107.43" y="165.66" batter="136460" pitcher="450212" type="O" team="A" inning="8"/><hip des="Lineout" x="152.61" y="167.67" batter="462405" pitcher="450212" type="O" team="A" inning="8"/><hip des="Flyout" x="138.55" y="49.20" batter="457788" pitcher="450212" type="O" team="A" inning="8"/><hip des="Groundout" x="107.43" y="152.61" batter="407886" pitcher="450852" type="O" team="H" inning="8"/><hip des="Groundout" x="126.51" y="152.61" batter="519203" pitcher="450852" type="O" team="H" inning="8"/><hip des="Flyout" x="136.55" y="62.25" batter="457727" pitcher="450852" type="O" team="H" inning="8"/><hip des="Pop Out" x="147.59" y="138.55" batter="116706" pitcher="543805" type="O" team="A" inning="9"/><hip des="Groundout" x="155.62" y="147.59" batter="435263" pitcher="543805" type="O" team="A" inning="9"/></hitchart>