<!--Copyright 2014 MLB Advanced Media, L.P.  Use of any content on this page acknowledges agreement to the terms posted here http://gdx.mlb.com/components/copyright.txt--><boxscore game_id="2011/06/05/nyamlb-anamlb-1" game_pk="287791" venue_id="1" venue_name="Angel Stadium of Anaheim" home_sport_code="mlb" away_team_code="nya" home_team_code="ana" away_id="147" home_id="108" away_fname="New York Yankees" home_fname="Los Angeles Angels" away_sname="NY Yankees" home_sname="LA Angels" date="June 5, 2011" away_wins="33" away_loss="24" home_wins="30" home_loss="31" status_ind="F">
   <linescore away_team_runs="5" home_team_runs="3" away_team_hits="11" home_team_hits="10" away_team_errors="0" home_team_errors="0">
      <inning_line_score away="0" home="0" inning="1"></inning_line_score>
      <inning_line_score away="1" home="0" inning="2"></inning_line_score>
      <inning_line_score away="1" home="2" inning="3"></inning_line_score>
      <inning_line_score away="0" home="0" inning="4"></inning_line_score>
      <inning_line_score away="2" home="1" inning="5"></inning_line_score>
      <inning_line_score away="0" home="0" inning="6"></inning_line_score>
      <inning_line_score away="0" home="0" inning="7"></inning_line_score>
      <inning_line_score away="1" home="0" inning="8"></inning_line_score>
      <inning_line_score away="0" home="0" inning="9"></inning_line_score>
   </linescore>
   <pitching team_flag="away" out="27" h="10" r="3" er="3" bb="5" so="7" hr="1" bf="40" era="3.45">
      <pitcher id="112526" name="Colon" name_display_first_last="Bartolo Colon" pos="P" out="16" bf="24" er="3" r="3" h="6" so="4" hr="1" bb="2" np="90" s="56" w="4" l="3" sv="0" bs="0" hld="0" s_ip="71.2" s_h="64" s_r="29" s_er="27" s_bb="17" s_so="66" era="3.39" win="true" note="(W, 4-3)"></pitcher>
      <pitcher id="502085" name="Robertson, D" name_display_first_last="David Robertson" pos="P" out="3" bf="5" er="0" r="0" h="0" so="1" hr="0" bb="2" np="27" s="15" w="1" l="0" sv="0" bs="2" hld="10" s_ip="23.1" s_h="16" s_r="4" s_er="3" s_bb="18" s_so="38" era="1.16" note="(H, 10)"></pitcher>
      <pitcher id="501955" name="Chamberlain" name_display_first_last="Joba Chamberlain" pos="P" out="5" bf="7" er="0" r="0" h="2" so="1" hr="0" bb="1" np="35" s="19" w="2" l="0" sv="0" bs="1" hld="12" s_ip="28.2" s_h="23" s_r="10" s_er="9" s_bb="7" s_so="24" era="2.83" note="(H, 12)"></pitcher>
      <pitcher id="121250" name="Rivera" name_display_first_last="Mariano Rivera" pos="P" out="3" bf="4" er="0" r="0" h="2" so="1" hr="0" bb="0" np="13" s="11" w="1" l="1" sv="16" bs="3" hld="0" s_ip="23.2" s_h="21" s_r="5" s_er="5" s_bb="4" s_so="19" era="1.90" save="true" note="(S, 16)"></pitcher>
   </pitching>
   <batting team_flag="home" ab="34" r="3" h="10" d="3" t="0" hr="1" rbi="3" bb="5" po="27" da="18" so="7" lob="17" avg=".257">
      <batter id="430895" name="Izturis, M" name_display_first_last="Maicer Izturis" pos="2B" bo="100" ab="4" po="2" r="1" a="3" bb="0" sac="0" t="0" sf="1" h="2" e="0" d="1" hbp="0" so="2" hr="0" rbi="1" lob="3" fldg="1.000" sb="0" cs="0" s_hr="3" s_rbi="16" s_h="57" s_bb="18" s_r="24" s_so="28" avg=".285" ao="1"></batter>
      <batter id="430947" name="Aybar" name_display_first_last="Erick Aybar" pos="SS" bo="200" ab="5" po="2" r="0" a="6" bb="0" sac="0" t="0" sf="0" h="1" e="0" d="0" hbp="0" so="2" hr="0" rbi="1" lob="2" fldg="1.000" sb="0" cs="0" s_hr="3" s_rbi="21" s_h="58" s_bb="10" s_r="23" s_so="29" avg=".302" go="2" ao="0"></batter>
      <batter id="110029" name="Abreu" name_display_first_last="Bobby Abreu" pos="DH" bo="300" ab="3" po="0" r="0" a="0" bb="2" sac="0" t="0" sf="0" h="2" e="0" d="0" hbp="0" so="0" hr="0" rbi="0" lob="0" fldg=".000" sb="1" cs="0" s_hr="2" s_rbi="25" s_h="63" s_bb="41" s_r="25" s_so="44" avg=".292" go="1" ao="0"></batter>
      <batter id="116338" name="Hunter, To" name_display_first_last="Torii Hunter" pos="RF" bo="400" ab="5" po="2" r="0" a="0" bb="0" sac="0" t="0" sf="0" h="0" e="0" d="0" hbp="0" so="0" hr="0" rbi="0" lob="7" fldg="1.000" sb="0" cs="0" s_hr="8" s_rbi="31" s_h="53" s_bb="28" s_r="24" s_so="51" avg=".229" go="4" ao="2" gidp="1"></batter>
      <batter id="430948" name="Callaspo" name_display_first_last="Alberto Callaspo" pos="3B" bo="500" ab="4" po="1" r="0" a="3" bb="0" sac="0" t="0" sf="0" h="2" e="0" d="1" hbp="0" so="1" hr="0" rbi="0" lob="0" fldg="1.000" sb="0" cs="0" s_hr="3" s_rbi="28" s_h="65" s_bb="22" s_r="20" s_so="17" avg=".305" go="1" ao="0"></batter>
      <batter id="435062" name="Kendrick, H" name_display_first_last="Howie Kendrick" pos="LF" bo="600" ab="4" po="0" r="0" a="1" bb="0" sac="0" t="0" sf="0" h="0" e="0" d="0" hbp="0" so="1" hr="0" rbi="0" lob="3" fldg="1.000" sb="0" cs="0" s_hr="7" s_rbi="18" s_h="57" s_bb="16" s_r="30" s_so="42" avg=".310" go="3" ao="0"></batter>
      <batter id="444432" name="Trumbo" name_display_first_last="Mark Trumbo" pos="1B" bo="700" ab="4" po="13" r="1" a="2" bb="0" sac="0" t="0" sf="0" h="1" e="0" d="0" hbp="0" so="0" hr="1" rbi="1" lob="1" fldg="1.000" sb="1" cs="0" s_hr="11" s_rbi="29" s_h="51" s_bb="13" s_r="22" s_so="45" avg=".262" go="2" ao="1"></batter>
      <batter id="474233" name="Conger" name_display_first_last="Hank Conger" pos="C" bo="800" ab="2" po="6" r="1" a="1" bb="2" sac="0" t="0" sf="0" h="1" e="0" d="1" hbp="0" so="0" hr="0" rbi="0" lob="0" fldg="1.000" sb="0" cs="0" s_hr="3" s_rbi="12" s_h="26" s_bb="9" s_r="9" s_so="21" avg=".239" ao="1"></batter>
      <batter id="488721" name="Bourjos" name_display_first_last="Peter Bourjos" pos="CF" bo="900" ab="3" po="0" r="0" a="0" bb="1" sac="0" t="0" sf="0" h="1" e="0" d="0" hbp="0" so="1" hr="0" rbi="0" lob="1" fldg=".000" sb="1" cs="0" s_hr="3" s_rbi="13" s_h="51" s_bb="15" s_r="27" s_so="61" avg=".244" go="2" ao="0" gidp="1"></batter>
      <batter id="334492" name="Pineiro" name_display_first_last="Joel Pineiro" pos="P" ab="0" po="1" r="0" a="1" bb="0" sac="0" t="0" sf="0" h="0" e="0" d="0" hbp="0" so="0" hr="0" rbi="0" lob="0" fldg="1.000" sb="0" cs="0" s_hr="0" s_rbi="0" s_h="0" s_bb="0" s_r="0" s_so="0" avg=".000" ao="0"></batter>
      <batter id="538227" name="Takahashi" name_display_first_last="Hisanori Takahashi" pos="P" ab="0" po="0" r="0" a="0" bb="0" sac="0" t="0" sf="0" h="0" e="0" d="0" hbp="0" so="0" hr="0" rbi="0" lob="0" fldg=".000" sb="0" cs="0" s_hr="0" s_rbi="0" s_h="0" s_bb="0" s_r="0" s_so="0" avg=".000" ao="0"></batter>
      <batter id="448178" name="Jepsen" name_display_first_last="Kevin Jepsen" pos="P" ab="0" po="0" r="0" a="0" bb="0" sac="0" t="0" sf="0" h="0" e="0" d="0" hbp="0" so="0" hr="0" rbi="0" lob="0" fldg=".000" sb="0" cs="0" s_hr="0" s_rbi="0" s_h="0" s_bb="0" s_r="0" s_so="0" avg=".000" ao="0"></batter>
      <batter id="457707" name="Bell, T" name_display_first_last="Trevor Bell" pos="P" ab="0" po="0" r="0" a="1" bb="0" sac="0" t="0" sf="0" h="0" e="0" d="0" hbp="0" so="0" hr="0" rbi="0" lob="0" fldg="1.000" sb="0" cs="0" s_hr="0" s_rbi="0" s_h="0" s_bb="0" s_r="0" s_so="0" avg=".000" ao="0"></batter>
      <text_data><![CDATA[<b>BATTING</b><br/><span><b>2B</b>: Conger (6, Colon), Izturis, M (16, Colon), Callaspo (11, Colon).</span><br/><span><b>HR</b>: Trumbo (11, 3rd inning off Colon, 0 on, 0 out).</span><br/><span><b>TB</b>: Callaspo 3; Aybar; Bourjos; Trumbo 4; Conger 2; Abreu 2; Izturis, M 3.</span><br/><span><b>RBI</b>: Trumbo (29), Izturis, M (16), Aybar (21).</span><br/><span><b>2-out RBI</b>: Aybar.</span><br/><span><b>Runners left in scoring position, 2 out</b>: Hunter, To 3; Izturis, M 2; Kendrick, H.</span><br/><span><b>SF</b>: Izturis, M.</span><br/><span><b>GIDP</b>: Bourjos, Hunter, To.</span><br/><b>Team RISP</b>: 2-for-9.<br/><b>Team LOB</b>: 10.<br/><br/><b>BASERUNNING</b><br/><span><b>SB</b>: Bourjos (8, 3rd base off Colon/Cervelli), Abreu (10, 2nd base off Colon/Cervelli), Trumbo (6, 2nd base off Robertson, D/Cervelli).</span><br/><br/><b>FIELDING</b><br/><span><b>Outfield assists</b>: Kendrick, H (Posada at 3rd base).</span><br/><span><b>DP</b>: 2 (Trumbo-Aybar-Pineiro, Aybar-Izturis, M-Trumbo).</span><br/><br/>]]>
      </text_data>
   </batting>
   <pitching team_flag="home" out="27" h="11" r="5" er="5" bb="3" so="6" hr="3" bf="37" era="3.41">
      <pitcher id="334492" name="Pineiro" name_display_first_last="Joel Pineiro" pos="P" out="20" bf="29" er="4" r="4" h="9" so="4" hr="2" bb="3" np="102" s="65" w="2" l="3" sv="0" bs="0" hld="0" s_ip="52.2" s_h="62" s_r="24" s_er="22" s_bb="11" s_so="23" era="3.76" loss="true" note="(L, 2-3)"></pitcher>
      <pitcher id="538227" name="Takahashi" name_display_first_last="Hisanori Takahashi" pos="P" out="1" bf="1" er="0" r="0" h="0" so="0" hr="0" bb="0" np="3" s="2" w="1" l="1" sv="0" bs="1" hld="3" s_ip="22.2" s_h="27" s_r="13" s_er="12" s_bb="11" s_so="16" era="4.76"></pitcher>
      <pitcher id="448178" name="Jepsen" name_display_first_last="Kevin Jepsen" pos="P" out="3" bf="4" er="1" r="1" h="1" so="1" hr="1" bb="0" np="13" s="9" w="1" l="2" sv="0" bs="1" hld="2" s_ip="11.0" s_h="18" s_r="11" s_er="11" s_bb="7" s_so="5" era="9.00"></pitcher>
      <pitcher id="457707" name="Bell, T" name_display_first_last="Trevor Bell" pos="P" out="3" bf="3" er="0" r="0" h="1" so="1" hr="0" bb="0" np="13" s="10" w="1" l="1" sv="0" bs="0" hld="0" s_ip="15.0" s_h="16" s_r="6" s_er="5" s_bb="5" s_so="7" era="3.00"></pitcher>
   </pitching>
   <batting team_flag="away" ab="34" r="5" h="11" d="3" t="0" hr="3" rbi="5" bb="3" po="27" da="14" so="6" lob="8" avg=".251">
      <batter id="116539" name="Jeter" name_display_first_last="Derek Jeter" pos="SS" bo="100" ab="5" po="1" r="0" a="3" bb="0" sac="0" t="0" sf="0" h="1" e="0" d="0" hbp="0" so="0" hr="0" rbi="0" lob="0" fldg="1.000" sb="0" cs="0" s_hr="2" s_rbi="16" s_h="60" s_bb="22" s_r="34" s_so="27" avg=".260" go="4" ao="0"></batter>
      <batter id="434158" name="Granderson" name_display_first_last="Curtis Granderson" pos="CF" bo="200" ab="3" po="1" r="1" a="0" bb="1" sac="0" t="0" sf="0" h="1" e="0" d="0" hbp="0" so="1" hr="0" rbi="0" lob="1" fldg="1.000" sb="1" cs="0" s_hr="17" s_rbi="41" s_h="60" s_bb="24" s_r="46" s_so="56" avg=".274" go="2" ao="0" gidp="1"></batter>
      <batter id="407893" name="Teixeira" name_display_first_last="Mark Teixeira" pos="1B" bo="300" ab="4" po="11" r="2" a="1" bb="0" sac="0" t="0" sf="0" h="3" e="0" d="0" hbp="0" so="0" hr="2" rbi="3" lob="1" fldg="1.000" sb="0" cs="0" s_hr="18" s_rbi="41" s_h="55" s_bb="32" s_r="35" s_so="40" avg=".258" go="1" ao="0"></batter>
      <batter id="121347" name="Rodriguez, Al" name_display_first_last="Alex Rodriguez" pos="3B" bo="400" ab="3" po="1" r="0" a="3" bb="1" sac="0" t="0" sf="0" h="0" e="0" d="0" hbp="0" so="1" hr="0" rbi="0" lob="1" fldg="1.000" sb="0" cs="0" s_hr="10" s_rbi="33" s_h="58" s_bb="22" s_r="35" s_so="45" avg=".287" go="1" ao="1"></batter>
      <batter id="429664" name="Cano" name_display_first_last="Robinson Cano" pos="2B" bo="500" ab="4" po="3" r="1" a="4" bb="0" sac="0" t="0" sf="0" h="1" e="0" d="1" hbp="0" so="1" hr="0" rbi="0" lob="1" fldg="1.000" sb="0" cs="0" s_hr="12" s_rbi="38" s_h="61" s_bb="9" s_r="33" s_so="33" avg=".277" go="1" ao="1"></batter>
      <batter id="430897" name="Swisher" name_display_first_last="Nick Swisher" pos="RF" bo="600" ab="3" po="2" r="1" a="0" bb="1" sac="0" t="0" sf="0" h="1" e="0" d="0" hbp="0" so="0" hr="1" rbi="1" lob="0" fldg="1.000" sb="0" cs="0" s_hr="5" s_rbi="24" s_h="39" s_bb="35" s_r="25" s_so="44" avg=".215" go="1" ao="1"></batter>
      <batter id="447736" name="Dickerson" name_display_first_last="Chris Dickerson" pos="RF" bo="601" ab="0" po="0" r="0" a="0" bb="0" sac="0" t="0" sf="0" h="0" e="0" d="0" hbp="0" so="0" hr="0" rbi="0" lob="0" fldg=".000" sb="0" cs="0" s_hr="0" s_rbi="3" s_h="4" s_bb="1" s_r="3" s_so="5" avg=".308" ao="0"></batter>
      <batter id="120691" name="Posada" name_display_first_last="Jorge Posada" pos="DH" bo="700" ab="4" po="0" r="0" a="0" bb="0" sac="0" t="0" sf="0" h="2" e="0" d="1" hbp="0" so="0" hr="0" rbi="0" lob="2" fldg=".000" sb="0" cs="0" s_hr="6" s_rbi="17" s_h="26" s_bb="22" s_r="13" s_so="37" avg=".178" go="3" ao="0" gidp="1"></batter>
      <batter id="458731" name="Gardner, B" name_display_first_last="Brett Gardner" pos="LF" bo="800" ab="4" po="0" r="0" a="0" bb="0" sac="0" t="0" sf="0" h="2" e="0" d="1" hbp="0" so="0" hr="0" rbi="1" lob="1" fldg=".000" sb="0" cs="1" s_hr="3" s_rbi="14" s_h="42" s_bb="18" s_r="25" s_so="37" avg=".258" go="1" ao="1"></batter>
      <batter id="465041" name="Cervelli" name_display_first_last="Francisco Cervelli" pos="C" bo="900" ab="4" po="7" r="0" a="0" bb="0" sac="0" t="0" sf="0" h="0" e="0" d="0" hbp="0" so="3" hr="0" rbi="0" lob="1" fldg="1.000" sb="0" cs="0" s_hr="1" s_rbi="8" s_h="5" s_bb="2" s_r="3" s_so="8" avg=".167" go="1" ao="0"></batter>
      <batter id="112526" name="Colon" name_display_first_last="Bartolo Colon" pos="P" ab="0" po="1" r="0" a="3" bb="0" sac="0" t="0" sf="0" h="0" e="0" d="0" hbp="0" so="0" hr="0" rbi="0" lob="0" fldg="1.000" sb="0" cs="0" s_hr="0" s_rbi="0" s_h="0" s_bb="0" s_r="0" s_so="0" avg=".000" ao="0"></batter>
      <batter id="502085" name="Robertson, D" name_display_first_last="David Robertson" pos="P" ab="0" po="0" r="0" a="0" bb="0" sac="0" t="0" sf="0" h="0" e="0" d="0" hbp="0" so="0" hr="0" rbi="0" lob="0" fldg=".000" sb="0" cs="0" s_hr="0" s_rbi="0" s_h="0" s_bb="0" s_r="0" s_so="0" avg=".000" ao="0"></batter>
      <batter id="501955" name="Chamberlain" name_display_first_last="Joba Chamberlain" pos="P" ab="0" po="0" r="0" a="0" bb="0" sac="0" t="0" sf="0" h="0" e="0" d="0" hbp="0" so="0" hr="0" rbi="0" lob="0" fldg=".000" sb="0" cs="0" s_hr="0" s_rbi="0" s_h="0" s_bb="0" s_r="0" s_so="0" avg=".000" ao="0"></batter>
      <batter id="121250" name="Rivera" name_display_first_last="Mariano Rivera" pos="P" ab="0" po="0" r="0" a="0" bb="0" sac="0" t="0" sf="0" h="0" e="0" d="0" hbp="0" so="0" hr="0" rbi="0" lob="0" fldg=".000" sb="0" cs="0" s_hr="0" s_rbi="0" s_h="0" s_bb="0" s_r="0" s_so="0" avg=".000" ao="0"></batter>
      <text_data><![CDATA[<b>BATTING</b><br/><span><b>2B</b>: Cano (12, Pineiro), Gardner, B (6, Pineiro), Posada (7, Pineiro).</span><br/><span><b>HR</b>: Teixeira 2 (18, 3rd inning off Pineiro, 0 on, 2 out; 5th inning off Pineiro, 1 on, 2 out), Swisher (5, 8th inning off Jepsen, 0 on, 2 out).</span><br/><span><b>TB</b>: Posada 3; Cano 2; Teixeira 9; Jeter; Gardner, B 3; Swisher 4; Granderson.</span><br/><span><b>RBI</b>: Gardner, B (14), Teixeira 3 (41), Swisher (24).</span><br/><span><b>2-out RBI</b>: Gardner, B; Teixeira 3; Swisher.</span><br/><span><b>Runners left in scoring position, 2 out</b>: Cervelli; Teixeira.</span><br/><span><b>GIDP</b>: Posada, Granderson.</span><br/><b>Team RISP</b>: 1-for-4.<br/><b>Team LOB</b>: 5.<br/><br/><b>BASERUNNING</b><br/><span><b>SB</b>: Granderson (9, 2nd base off Takahashi/Conger).</span><br/><span><b>CS</b>: Gardner, B (7, 2nd base by Bell, T/Conger).</span><br/><br/><b>FIELDING</b><br/><span><b>DP</b>: 2 (Jeter-Teixeira, Rodriguez, Al-Cano-Teixeira).</span><br/><br/>]]>
      </text_data>
   </batting>
   <game_info><![CDATA[<span><b>IBB</b>: Abreu (by Colon).</span><br/><span><b>Pitches-strikes</b>: Colon 90-56, Robertson, D 27-15, Chamberlain 35-19, Rivera 13-11, Pineiro 102-65, Takahashi 3-2, Jepsen 13-9, Bell, T 13-10.</span><br/><span><b>Groundouts-flyouts</b>: Colon 8-2, Robertson, D 2-0, Chamberlain 2-0, Rivera 1-0, Pineiro 9-2, Takahashi 1-0, Jepsen 2-0, Bell, T 1-0.</span><br/><span><b>Batters faced</b>: Colon 24, Robertson, D 5, Chamberlain 7, Rivera 4, Pineiro 29, Takahashi 1, Jepsen 4, Bell, T 3.</span><br/><span><b>Inherited runners-scored</b>: Robertson, D 1-0, Takahashi 1-0.</span><br/><b>Umpires</b>: HP: Bill Welke. 1B: Tim Tschida. 2B: Mike Estabrook. 3B: John Tumpane. <br/><b>Weather</b>: 73 degrees, sunny.<br/><b>Wind</b>: 6 mph, Out to CF.<br/><b>T</b>: 3:20.<br/><b>Att</b>: 43,524.<br/><b>Venue</b>: Angel Stadium of Anaheim.<br/><b>June 5, 2011</b><br/>]]>
   </game_info>
</boxscore>