<!--Copyright 2014 MLB Advanced Media, L.P.  Use of any content on this page acknowledges agreement to the terms posted here http://gdx.mlb.com/components/copyright.txt--><game venue="Wrigley Field" date="June 19, 2011">
	<team type="away" id="NYY" name="New York Yankees">
		<player id="112526" first="Bartolo" last="Colon" num="40" boxname="Colon" rl="R" bats="R" position="P" status="A" team_abbrev="NYY" team_id="147" parent_team_abbrev="" parent_team_id="" avg=".000" hr="0" rbi="0" wins="5" losses="3" era="3.10"/>
		<player id="116539" first="Derek" last="Jeter" num="2" boxname="Jeter" rl="R" bats="R" position="SS" status="A" team_abbrev="NYY" team_id="147" parent_team_abbrev="NYY" parent_team_id="147" avg=".260" hr="2" rbi="20"/>
		<player id="116662" first="Andruw" last="Jones" num="18" boxname="Jones, An" rl="R" bats="R" position="RF" status="A" team_abbrev="NYY" team_id="147" parent_team_abbrev="" parent_team_id="" avg=".208" hr="4" rbi="11"/>
		<player id="120691" first="Jorge" last="Posada" num="20" boxname="Posada" rl="R" bats="S" position="C" current_position="PH" status="A" team_abbrev="NYY" team_id="147" parent_team_abbrev="" parent_team_id="" avg=".225" hr="6" rbi="21"/>
		<player id="121250" first="Mariano" last="Rivera" num="42" boxname="Rivera" rl="R" bats="R" position="P" status="A" team_abbrev="NYY" team_id="147" parent_team_abbrev="" parent_team_id="" avg=".000" hr="0" rbi="0" wins="1" losses="1" era="1.98"/>
		<player id="121347" first="Alex" last="Rodriguez" num="13" boxname="Rodriguez, Al" rl="R" bats="R" position="3B" current_position="3B" status="A" team_abbrev="NYY" team_id="147" parent_team_abbrev="" parent_team_id="" bat_order="4" game_position="3B" avg=".282" hr="13" rbi="42"/>
		<player id="136767" first="Eric" last="Chavez" num="12" boxname="Chavez, Er" rl="R" bats="L" position="3B" status="A" team_abbrev="NYY" team_id="147" parent_team_abbrev="" parent_team_id="" avg=".303" hr="0" rbi="6"/>
		<player id="150119" first="Freddy" last="Garcia" num="36" boxname="Garcia, F" rl="R" bats="R" position="P" status="A" team_abbrev="NYY" team_id="147" parent_team_abbrev="" parent_team_id="" avg=".000" hr="0" rbi="0" wins="5" losses="6" era="3.63"/>
		<player id="150122" first="Damaso" last="Marte" num="43" boxname="Marte" rl="L" bats="L" position="P" status="A" team_abbrev="NYY" team_id="147" parent_team_abbrev="" parent_team_id="" avg=".000" hr="0" rbi="0" wins="0" losses="0" era="-"/>
		<player id="150359" first="A.J." last="Burnett" num="34" boxname="Burnett, AJ" rl="R" bats="R" position="P" status="A" team_abbrev="NYY" team_id="147" parent_team_abbrev="" parent_team_id="" avg=".000" hr="0" rbi="0" wins="7" losses="5" era="4.05"/>
		<player id="282332" first="CC" last="Sabathia" num="52" boxname="Sabathia" rl="L" bats="L" position="P" current_position="P" status="A" team_abbrev="NYY" team_id="147" parent_team_abbrev="NYY" parent_team_id="147" bat_order="9" game_position="P" avg=".000" hr="0" rbi="0" wins="8" losses="4" era="3.28"/>
		<player id="400089" first="Rafael" last="Soriano" num="29" boxname="Soriano, R" rl="R" bats="R" position="P" status="A" team_abbrev="NYY" team_id="147" parent_team_abbrev="" parent_team_id="" avg=".000" hr="0" rbi="0" wins="1" losses="1" era="5.40"/>
		<player id="407893" first="Mark" last="Teixeira" num="25" boxname="Teixeira" rl="R" bats="S" position="1B" current_position="1B" status="A" team_abbrev="NYY" team_id="147" parent_team_abbrev="NYY" parent_team_id="147" bat_order="3" game_position="1B" avg=".251" hr="21" rbi="54"/>
		<player id="408230" first="Pedro" last="Feliciano" num="31" boxname="Feliciano, P" rl="L" bats="L" position="P" status="A" team_abbrev="NYY" team_id="147" parent_team_abbrev="" parent_team_id="" avg=".000" hr="0" rbi="0" wins="0" losses="0" era="-"/>
		<player id="425646" first="Luis" last="Ayala" num="38" boxname="Ayala" rl="R" bats="R" position="P" status="A" team_abbrev="NYY" team_id="147" parent_team_abbrev="" parent_team_id="" avg=".000" hr="0" rbi="0" wins="1" losses="1" era="1.19"/>
		<player id="429664" first="Robinson" last="Cano" num="24" boxname="Cano" rl="R" bats="L" position="2B" current_position="2B" status="A" team_abbrev="NYY" team_id="147" parent_team_abbrev="" parent_team_id="" bat_order="5" game_position="2B" avg=".293" hr="14" rbi="46"/>
		<player id="430897" first="Nick" last="Swisher" num="33" boxname="Swisher" rl="L" bats="S" position="RF" current_position="RF" status="A" team_abbrev="NYY" team_id="147" parent_team_abbrev="" parent_team_id="" bat_order="6" game_position="RF" avg=".228" hr="6" rbi="29"/>
		<player id="430950" first="Brian" last="Gordon" num="22" boxname="Gordon, B" rl="R" bats="L" position="P" status="A" team_abbrev="NYY" team_id="147" parent_team_abbrev="NYY" parent_team_id="147" avg=".000" hr="0" rbi="0" wins="0" losses="0" era="3.38"/>
		<player id="431145" first="Russell" last="Martin" num="55" boxname="Martin, R" rl="R" bats="R" position="C" current_position="C" status="A" team_abbrev="NYY" team_id="147" parent_team_abbrev="" parent_team_id="" bat_order="7" game_position="C" avg=".236" hr="9" rbi="28"/>
		<player id="434158" first="Curtis" last="Granderson" num="14" boxname="Granderson" rl="R" bats="L" position="CF" current_position="CF" status="A" team_abbrev="NYY" team_id="147" parent_team_abbrev="" parent_team_id="" bat_order="2" game_position="CF" avg=".285" hr="21" rbi="53"/>
		<player id="447736" first="Chris" last="Dickerson" num="27" boxname="Dickerson" rl="L" bats="L" position="LF" current_position="RF" status="A" team_abbrev="NYY" team_id="147" parent_team_abbrev="" parent_team_id="" avg=".313" hr="0" rbi="3"/>
		<player id="453298" first="Colin" last="Curtis" num="61" boxname="Curtis" rl="L" bats="L" position="LF" status="A" team_abbrev="NYY" team_id="147" parent_team_abbrev="" parent_team_id="" avg=".000" hr="0" rbi="0"/>
		<player id="455369" first="Ramiro" last="Pena" num="19" boxname="Pena, R" rl="R" bats="S" position="SS" current_position="3B" status="A" team_abbrev="NYY" team_id="147" parent_team_abbrev="" parent_team_id="" avg=".286" hr="1" rbi="1"/>
		<player id="456051" first="Hector" last="Noesi" num="64" boxname="Noesi" rl="R" bats="R" position="P" status="A" team_abbrev="NYY" team_id="147" parent_team_abbrev="" parent_team_id="" avg=".000" hr="0" rbi="0" wins="1" losses="0" era="1.50"/>
		<player id="456488" first="Eduardo" last="Nunez" num="26" boxname="Nunez" rl="R" bats="R" position="3B" current_position="SS" status="A" team_abbrev="NYY" team_id="147" parent_team_abbrev="NYY" parent_team_id="147" bat_order="8" game_position="SS" avg=".257" hr="2" rbi="10"/>
		<player id="457429" first="Boone" last="Logan" num="48" boxname="Logan" rl="L" bats="R" position="P" status="A" team_abbrev="NYY" team_id="147" parent_team_abbrev="" parent_team_id="" avg=".000" hr="0" rbi="0" wins="1" losses="2" era="3.38"/>
		<player id="457812" first="Jeff" last="Marquez" num="41" boxname="Marquez" rl="R" bats="R" position="P" current_position="P" status="A" team_abbrev="NYY" team_id="147" parent_team_abbrev="" parent_team_id="" avg=".000" hr="0" rbi="0" wins="0" losses="0" era="3.00"/>
		<player id="458731" first="Brett" last="Gardner" num="11" boxname="Gardner, B" rl="L" bats="L" position="LF" current_position="LF" status="A" team_abbrev="NYY" team_id="147" parent_team_abbrev="NYY" parent_team_id="147" bat_order="1" game_position="LF" avg=".286" hr="3" rbi="17"/>
		<player id="460677" first="Cory" last="Wade" num="53" boxname="Wade" rl="R" bats="R" position="P" status="A" team_abbrev="NYY" team_id="147" parent_team_abbrev="" parent_team_id="" avg=".000" hr="0" rbi="0" wins="1" losses="0" era="0.00"/>
		<player id="461833" first="Phil" last="Hughes" num="65" boxname="Hughes, P" rl="R" bats="R" position="P" status="A" team_abbrev="NYY" team_id="147" parent_team_abbrev="" parent_team_id="" avg=".000" hr="0" rbi="0" wins="0" losses="1" era="13.94"/>
		<player id="465041" first="Francisco" last="Cervelli" num="17" boxname="Cervelli" rl="R" bats="R" position="C" status="A" team_abbrev="NYY" team_id="147" parent_team_abbrev="NYY" parent_team_id="147" avg=".185" hr="1" rbi="11"/>
		<player id="467100" first="Ivan" last="Nova" num="47" boxname="Nova" rl="R" bats="R" position="P" status="A" team_abbrev="NYY" team_id="147" parent_team_abbrev="NYY" parent_team_id="147" avg=".000" hr="0" rbi="0" wins="6" losses="4" era="4.46"/>
		<player id="468470" first="Reegie" last="Corona" num="76" boxname="Corona" rl="R" bats="S" position="2B" status="A" team_abbrev="NYY" team_id="147" parent_team_abbrev="" parent_team_id="" avg=".000" hr="0" rbi="0"/>
		<player id="501955" first="Joba" last="Chamberlain" num="62" boxname="Chamberlain" rl="R" bats="R" position="P" status="A" team_abbrev="NYY" team_id="147" parent_team_abbrev="" parent_team_id="" avg=".000" hr="0" rbi="0" wins="2" losses="0" era="2.83"/>
		<player id="502085" first="David" last="Robertson" num="30" boxname="Robertson, D" rl="R" bats="R" position="P" current_position="P" status="A" team_abbrev="NYY" team_id="147" parent_team_abbrev="NYY" parent_team_id="147" avg=".000" hr="0" rbi="0" wins="1" losses="0" era="1.27"/>
<coach position="manager" first="Joe" last="Girardi" id="114833" num="28"/><coach position="batting_coach" first="Kevin" last="Long" id="438989" num="54"/><coach position="pitching_coach" first="Larry" last="Rothschild" id="121495" num="58"/><coach position="first_base_coach" first="Mick" last="Kelleher" id="116918" num="50"/><coach position="third_base_coach" first="Rob" last="Thomson" id="479080" num="59"/><coach position="bench_coach" first="Tony" last="Pena" id="120370" num="56"/><coach position="bullpen_coach" first="Mike" last="Harkey" id="115476" num="57"/><coach position="bullpen_catcher" first="Roman" last="Rodriguez" id="459550" num="88"/>	</team>
	<team type="home" id="CHC" name="Chicago Cubs">
		<player id="133225" first="Ryan" last="Dempster" num="46" boxname="Dempster" rl="R" bats="R" position="P" status="A" team_abbrev="CHC" team_id="112" parent_team_abbrev="" parent_team_id="" avg=".071" hr="0" rbi="0" wins="5" losses="6" era="5.46"/>
		<player id="133380" first="Aramis" last="Ramirez" num="16" boxname="Ramirez, Ar" rl="R" bats="R" position="3B" current_position="3B" status="A" team_abbrev="CHC" team_id="112" parent_team_abbrev="" parent_team_id="" bat_order="4" game_position="3B" avg=".274" hr="5" rbi="32"/>
		<player id="134268" first="Kerry" last="Wood" num="34" boxname="Wood, K" rl="R" bats="R" position="P" status="A" team_abbrev="CHC" team_id="112" parent_team_abbrev="" parent_team_id="" avg=".000" hr="0" rbi="0" wins="1" losses="3" era="2.25"/>
		<player id="150093" first="Alfonso" last="Soriano" num="12" boxname="Soriano, A" rl="R" bats="R" position="LF" current_position="LF" status="A" team_abbrev="CHC" team_id="112" parent_team_abbrev="" parent_team_id="" bat_order="5" game_position="LF" avg=".275" hr="13" rbi="31"/>
		<player id="150277" first="Doug" last="Davis" num="32" boxname="Davis, D" rl="L" bats="R" position="P" status="A" team_abbrev="CHC" team_id="112" parent_team_abbrev="" parent_team_id="" avg=".000" hr="0" rbi="0" wins="1" losses="5" era="4.95"/>
		<player id="150289" first="Carlos" last="Pena" num="22" boxname="Pena, C" rl="L" bats="L" position="1B" current_position="1B" status="A" team_abbrev="CHC" team_id="112" parent_team_abbrev="" parent_team_id="" avg=".220" hr="11" rbi="33"/>
		<player id="150438" first="Rodrigo" last="Lopez" num="50" boxname="Lopez, R" rl="R" bats="R" position="P" current_position="P" status="A" team_abbrev="CHC" team_id="112" parent_team_abbrev="" parent_team_id="" avg=".000" hr="0" rbi="0" wins="0" losses="1" era="6.57"/>
		<player id="346848" first="John" last="Grabow" num="43" boxname="Grabow" rl="L" bats="L" position="P" status="A" team_abbrev="CHC" team_id="112" parent_team_abbrev="" parent_team_id="" avg=".000" hr="0" rbi="0" wins="0" losses="0" era="5.04"/>
		<player id="407296" first="Carlos" last="Zambrano" num="38" boxname="Zambrano" rl="R" bats="S" position="P" status="A" team_abbrev="CHC" team_id="112" parent_team_abbrev="" parent_team_id="" avg=".313" hr="1" rbi="4" wins="5" losses="4" era="4.59"/>
		<player id="407781" first="Marlon" last="Byrd" num="24" boxname="Byrd" rl="R" bats="R" position="CF" status="A" team_abbrev="CHC" team_id="112" parent_team_abbrev="" parent_team_id="" avg=".308" hr="3" rbi="11"/>
		<player id="407862" first="Reed" last="Johnson" num="5" boxname="Johnson, R" rl="R" bats="R" position="LF" current_position="CF" status="A" team_abbrev="CHC" team_id="112" parent_team_abbrev="" parent_team_id="" bat_order="1" game_position="CF" avg=".356" hr="4" rbi="22"/>
		<player id="425542" first="Koyie" last="Hill" num="55" boxname="Hill, K" rl="R" bats="S" position="C" status="A" team_abbrev="CHC" team_id="112" parent_team_abbrev="" parent_team_id="" avg=".233" hr="1" rbi="7"/>
		<player id="425557" first="Jeff" last="Baker" num="3" boxname="Baker, Je" rl="R" bats="R" position="1B" current_position="RF" status="A" team_abbrev="CHC" team_id="112" parent_team_abbrev="" parent_team_id="" bat_order="3" game_position="1B" avg=".343" hr="2" rbi="15"/>
		<player id="428642" first="Luis" last="Montanez" num="39" boxname="Montanez" rl="R" bats="R" position="LF" current_position="RF" status="A" team_abbrev="CHC" team_id="112" parent_team_abbrev="" parent_team_id="" bat_order="7" game_position="RF" avg=".281" hr="0" rbi="6"/>
		<player id="434567" first="Geovany" last="Soto" num="18" boxname="Soto, G" rl="R" bats="R" position="C" current_position="C" status="A" team_abbrev="CHC" team_id="112" parent_team_abbrev="" parent_team_id="" bat_order="6" game_position="C" avg=".216" hr="5" rbi="15"/>
		<player id="445156" first="Sean" last="Marshall" num="45" boxname="Marshall, S" rl="L" bats="L" position="P" current_position="P" status="A" team_abbrev="CHC" team_id="112" parent_team_abbrev="" parent_team_id="" avg=".000" hr="0" rbi="0" wins="3" losses="1" era="1.93"/>
		<player id="446381" first="Darwin" last="Barney" num="15" boxname="Barney" rl="R" bats="R" position="2B" status="A" team_abbrev="CHC" team_id="112" parent_team_abbrev="CHC" parent_team_id="112" avg=".294" hr="1" rbi="25"/>
		<player id="448694" first="Randy" last="Wells" num="36" boxname="Wells" rl="R" bats="R" position="P" current_position="P" status="A" team_abbrev="CHC" team_id="112" parent_team_abbrev="" parent_team_id="" bat_order="9" game_position="P" avg=".222" hr="0" rbi="0" wins="1" losses="1" era="5.63"/>
		<player id="452764" first="Chris" last="Carpenter" num="37" boxname="Carpenter, C" rl="R" bats="R" position="P" current_position="P" status="A" team_abbrev="CHC" team_id="112" parent_team_abbrev="" parent_team_id="" avg=".000" hr="0" rbi="0" wins="0" losses="0" era="0.00"/>
		<player id="455088" first="Blake" last="DeWitt" num="9" boxname="DeWitt" rl="R" bats="L" position="2B" current_position="2B" status="A" team_abbrev="CHC" team_id="112" parent_team_abbrev="" parent_team_id="" avg=".265" hr="1" rbi="6"/>
		<player id="460701" first="James" last="Russell" num="40" boxname="Russell" rl="L" bats="L" position="P" current_position="P" status="A" team_abbrev="CHC" team_id="112" parent_team_abbrev="CHC" parent_team_id="112" avg=".125" hr="0" rbi="0" wins="1" losses="5" era="5.21"/>
		<player id="461791" first="Carlos" last="Marmol" num="49" boxname="Marmol" rl="R" bats="R" position="P" status="A" team_abbrev="CHC" team_id="112" parent_team_abbrev="" parent_team_id="" avg=".000" hr="0" rbi="0" wins="1" losses="2" era="2.78"/>
		<player id="488768" first="Andrew" last="Cashner" num="48" boxname="Cashner" rl="R" bats="R" position="P" status="A" team_abbrev="CHC" team_id="112" parent_team_abbrev="" parent_team_id="" avg=".000" hr="0" rbi="0" wins="0" losses="0" era="1.69"/>
		<player id="489295" first="Brian" last="Schlitter" num="51" boxname="Schlitter" rl="R" bats="R" position="P" status="A" team_abbrev="CHC" team_id="112" parent_team_abbrev="CHC" parent_team_id="112" avg=".000" hr="0" rbi="0" wins="0" losses="0" era="-"/>
		<player id="490063" first="Matt" last="Garza" num="22" boxname="Garza, M" rl="R" bats="R" position="P" status="A" team_abbrev="CHC" team_id="112" parent_team_abbrev="" parent_team_id="" avg=".040" hr="0" rbi="0" wins="3" losses="6" era="4.14"/>
		<player id="493120" first="Kosuke" last="Fukudome" num="1" boxname="Fukudome" rl="R" bats="L" position="RF" current_position="PH" status="A" team_abbrev="CHC" team_id="112" parent_team_abbrev="" parent_team_id="" avg=".292" hr="3" rbi="10"/>
		<player id="502188" first="Jeff" last="Samardzija" num="29" boxname="Samardzija" rl="R" bats="R" position="P" status="A" team_abbrev="CHC" team_id="112" parent_team_abbrev="CHC" parent_team_id="112" avg=".000" hr="0" rbi="0" wins="5" losses="2" era="4.15"/>
		<player id="516770" first="Starlin" last="Castro" num="13" boxname="Castro, S" rl="R" bats="R" position="SS" current_position="SS" status="A" team_abbrev="CHC" team_id="112" parent_team_abbrev="CHC" parent_team_id="112" bat_order="2" game_position="SS" avg=".317" hr="1" rbi="32"/>
		<player id="518934" first="DJ" last="LeMahieu" num="33" boxname="LeMahieu" rl="R" bats="R" position="2B" current_position="2B" status="A" team_abbrev="CHC" team_id="112" parent_team_abbrev="" parent_team_id="" bat_order="8" game_position="2B" avg=".294" hr="0" rbi="1"/>
		<player id="542999" first="Tony" last="Campana" num="1" boxname="Campana" rl="L" bats="L" position="CF" current_position="PH" status="A" team_abbrev="CHC" team_id="112" parent_team_abbrev="" parent_team_id="" avg=".241" hr="0" rbi="2"/>
<coach position="manager" first="Mike" last="Quade" id="433641" num="8"/><coach position="batting_coach" first="Rudy" last="Jaramillo" id="427252" num="7"/><coach position="pitching_coach" first="Mark" last="Riggins" id="526909" num="47"/><coach position="first_base_coach" first="Bob" last="Dernier" id="113282" num="2"/><coach position="third_base_coach" first="Ivan" last="De Jesus" id="113212" num="11"/><coach position="bench_coach" first="Pat" last="Listach" id="117815" num="4"/><coach position="bullpen_coach" first="Lester" last="Strode" id="506427" num="35"/><coach position="bullpen_catcher" first="Andrew" last="Lane" id="489045" num="95"/><coach position="bullpen_catcher" first="Edgar" last="Tovar" id="471252" num="98"/><coach position="special_assistant" first="Dave" last="Keller" id="427267" num="25"/>	</team>
<umpires><umpire position="home" name="Todd Tichenor" id="429805"/><umpire position="first" name="Gerry Davis" id="427103"/><umpire position="second" name="Greg Gibson" id="427184"/><umpire position="third" name="Sam Holbrook" id="427235"/></umpires></game>